vwc/__init__.py
vwc/app.py
vwc/cli.py
vwc/count.py
vwc/format.py
vwc/platform.py
vwc-0.0.2.dist-info/entry_points.txt
vwc-0.0.2.dist-info/licenses/LICENSE.md
vwc-0.0.2.dist-info/WHEEL
vwc-0.0.2.dist-info/METADATA
vwc-0.0.2.dist-info/RECORD
