Metadata-Version: 2.4
Name: vwc
Version: 0.0.2
Summary: wc with a preview
Author-email: Random Hacker <no@dev.null>
Requires-Python: >=3.10
License-File: LICENSE.md
Requires-Dist: numba
Requires-Dist: pre-commit ; extra == "dev"
Requires-Dist: pytest ; extra == "dev"
Requires-Dist: coverage ; extra == "dev"
Requires-Dist: pytest-cov ; extra == "dev"
Requires-Dist: build ; extra == "dev"
Requires-Dist: twine ; extra == "dev"
Requires-Dist: ruff ; extra == "dev"
Requires-Dist: pydoc-markdown ; extra == "dev"
Provides-Extra: dev
